README.txt
setup.py
pywantickets/__init__.py
pywantickets/artist.py
pywantickets/cart.py
pywantickets/client.py
pywantickets/customer.py
pywantickets/event.py
pywantickets/facebook.py
pywantickets/factory.py
pywantickets/image.py
pywantickets/payment.py
pywantickets/paymentmethod.py
pywantickets/promoter.py
pywantickets/response.py
pywantickets/shipping.py
pywantickets/ticket.py
pywantickets/utils.py
pywantickets.egg-info/PKG-INFO
pywantickets.egg-info/SOURCES.txt
pywantickets.egg-info/dependency_links.txt
pywantickets.egg-info/not-zip-safe
pywantickets.egg-info/requires.txt
pywantickets.egg-info/top_level.txt