Metadata-Version: 1.1
Name: pywantickets
Version: 1.0.23
Summary: Wantickets.com implementation for Python.
Home-page: http://bitbucket.org/edesarrollos/pywantickets
Author: Gamaliel Espinoza
Author-email: gespinoza@edesarrollos.com
License: UNKNOWN
Platform: UNKNOWN
Classifier: Development Status :: 5 - Production/Stable
Classifier: Intended Audience :: Developers
Classifier: Natural Language :: English
Classifier: License :: OSI Approved :: Apache Software License
Classifier: Programming Language :: Python
Classifier: Programming Language :: Python :: 2.6
Classifier: Programming Language :: Python :: 2.7
Classifier: Programming Language :: Python :: 3
Classifier: Programming Language :: Python :: 3.3
